{
  "realmFixture": {
    "restOnline": true
  },
  "tauriFixture": {
    "runtimeDefaults": {
      "realm": {
        "realmBaseUrl": "__FIXTURE_ORIGIN__",
        "realtimeUrl": "__FIXTURE_ORIGIN__",
        "accessToken": "",
        "jwksUrl": "__FIXTURE_ORIGIN__/api/auth/jwks",
        "jwtIssuer": "__FIXTURE_ORIGIN__",
        "jwtAudience": "nimi-runtime"
      },
      "runtime": {
        "localProviderEndpoint": "http://127.0.0.1:1234/v1",
        "localProviderModel": "local-model",
        "localOpenAiEndpoint": "http://127.0.0.1:1234/v1",
        "credentialRefId": "",
        "targetType": "AGENT",
        "targetAccountId": "",
        "agentId": "",
        "worldId": "",
        "provider": "",
        "userConfirmedUpload": false
      }
    },
    "runtimeBridgeStatus": {
      "running": true,
      "managed": true,
      "launchMode": "RELEASE",
      "grpcAddr": "127.0.0.1:46371",
      "version": "0.1.0"
    },
    "desktopReleaseInfo": {
      "desktopVersion": "0.1.0",
      "runtimeVersion": "0.1.0",
      "channel": "stable",
      "commit": "e2e-fixture",
      "builtAt": "2026-03-15T00:00:00.000Z",
      "runtimeReady": true
    }
  },
  "artifactPolicy": {
    "failOnConsoleError": true,
    "failOnPageError": true
  }
}
